{"metadata": {"dbt_schema_version": "https://schemas.getdbt.com/dbt/run-results/v6.json", "dbt_version": "1.9.1", "generated_at": "2025-03-26T21:14:22.653690Z", "invocation_id": "6955363c-5135-430b-98ac-3db04c0981b8", "env": {}}, "results": [], "elapsed_time": 0.0, "args": {"state_modified_compare_more_unrendered_values": false, "require_yaml_configuration_for_mf_time_spines": false, "state_modified_compare_vars": false, "defer": false, "use_colors": true, "require_batched_execution_for_custom_microbatch_strategy": false, "log_level": "info", "project_dir": "/Users/jenniferwang/london-cycling-analytics", "macro_debugging": false, "empty": false, "printer_width": 80, "exclude": [], "log_format": "default", "which": "run", "print": true, "log_file_max_bytes": 10485760, "invocation_command": "dbt run --models mart.mart_day_of_week", "require_explicit_package_overrides_for_builtin_materializations": true, "favor_state": false, "profiles_dir": "/Users/jenniferwang/.dbt", "log_path": "/Users/jenniferwang/london-cycling-analytics/logs", "write_json": true, "populate_cache": true, "warn_error_options": {"include": [], "exclude": []}, "vars": {}, "cache_selected_only": false, "show_resource_report": false, "version_check": true, "partial_parse": true, "require_resource_names_without_spaces": false, "log_format_file": "debug", "source_freshness_run_project_hooks": false, "skip_nodes_if_on_run_start_fails": false, "indirect_selection": "eager", "use_colors_file": true, "introspect": true, "require_nested_cumulative_type_params": false, "select": ["mart.mart_day_of_week"], "static_parser": true, "log_level_file": "debug", "send_anonymous_usage_stats": true, "partial_parse_file_diff": true, "strict_mode": false, "quiet": false}}